{
  "station-type": "{\n\t station: string \n\t identifier: string \n\t name: string | null \n\t region: string | null \n\t country: string \n\t latitude: number \n\t longitude: number \n\t elevation: number | null \n}",
  "station-ex": "{\n\t station: \"71706\" \n\t identifier: \"40371706000\" \n\t name: \"CHARLOTTETOWN A,PE\" \n\t region: \"PE\" \n\t country: \"CANADA\" \n\t latitude: 46.28 \n\t longitude: -63.13 \n\t elevation: 48 \n}",
  "basic-station-type": "{\n\t station: string \n\t name: string | null \n}",
  "basic-station-ex": "{\n\t station: \"71706\" \n\t name: \"CHARLOTTETOWN A,PE\" \n}",
  "countries-type": "{\n\t code: number \n\t country: string \n\t supportedRegions: string array \n}",
  "countries-ex": "{\n\t code: 403 \n\t country: \"CANADA\" \n\t supportedRegions: [\"NW\", \"MA\", \"YT\", \"SA\", \"QU\", \"NB\", \"ON\", \"AL\", \"NS\", \"PE\", \"BC\", \"NF\"] \n}",
  "download-param-type-years": "{\n\t single: number | null \n\t start: number | null \n\t end: number | null \n}",
  "download-param-ex-years": "[\n\t{\n\t\t single: null \n\t\t start: 1950 \n\t\t end: 2000 \n\t},\n\t{\n\t\t single: 1930 \n\t\t start: null \n\t\t end: null \n\t},\n\t{\n\t\t single: null \n\t\t start: null \n\t\t end: 1870 \n\t}\n]",
  "download-param-ex-months": "[\"January\", \"February\", \"November\", \"December\"]",
  "download-param-ex-countries": "[\n\t{\n\t\t code: 403 \n\t\t country: \"CANADA\" \n\t\t supportedRegions: [\"NW\", \"MA\", \"YT\", \"SA\", \"QU\", \"NB\", \"ON\", \"AL\", \"NS\", \"PE\", \"BC\", \"NF\"] \n\t},\n\t{\n\t\t code: 115 \n\t\t \"EGYPT\" \n\t\t supportedRegions: [] \n\t}\n]",
  "download-param-ex-regions": "[\"YT\", \"NW\"]",
  "download-param-type-coordinates": "{\n\t latitude: {\n\t\t single: number | null \n\t\t start: number | null \n\t\t end: number | null \n\t },\n\t longitude: {\n\t\t single: number | null \n\t\t start: number | null \n\t\t end: number | null \n\t },\n\t elevation: {\n\t\t single: number | null \n\t\t start: number | null \n\t\t end: number | null \n\t }\n}",
  "download-param-ex-coordinates": "[\n\t{\n\t\t latitude: {\n\t\t\t single: null \n\t\t\t start: -20.5 \n\t\t\t end: -20 \n\t\t },\n\t\t longitude: {\n\t\t\t single: null \n\t\t\t start: 34 \n\t\t\t end: 35 \n\t\t },\n\t\t elevation: {\n\t\t\t single: null \n\t\t\t start: null \n\t\t\t end: null \n\t\t },\n\t},\n\t{\n\t\t latitude: {\n\t\t\t single: 50 \n\t\t\t start: null \n\t\t\t end: null \n\t\t },\n\t\t longitude: {\n\t\t\t single: null \n\t\t\t start: 179 \n\t\t\t end: null \n\t\t },\n\t\t elevation: {\n\t\t\t single: null \n\t\t\t start: 0 \n\t\t\t end: null \n\t\t }\n\t}\n]",
  "download-param-ex-stations": "[\n\t{\n\t\t name: \"ALGIERS\" \n\t\t station: \"60345.1\" \n\t},\n\t{\n\t\t name: \"SKIKDA\" \n\t\t station: \"60355\" \n\t}\n]",
  "download-param-ex-dataTypes": "[\"anom\", \"stations\"]",
  "download-type": "{\n\t prcp: {\n\t\t station: string \n\t\t year: number \n\t\t january?: number | null \n\t\t february?: number | null \n\t\t march?: number | null \n\t\t april?: number | null \n\t\t may?: number | null \n\t\t june?: number | null \n\t\t july?: number | null \n\t\t august?: number | null \n\t\t september?: number | null \n\t\t october?: number | null \n\t\t november?: number | null \n\t\t december?: number | null \n\t }[]\n\t anom: {\n\t\t station: string \n\t\t year: number \n\t\t january?: number | null \n\t\t february?: number | null \n\t\t march?: number | null \n\t\t april?: number | null \n\t\t may?: number | null \n\t\t june?: number | null \n\t\t july?: number | null \n\t\t august?: number | null \n\t\t september?: number | null \n\t\t october?: number | null \n\t\t november?: number | null \n\t\t december?: number | null \n\t }[]\n\t anom_pcnt: {\n\t\t station: string \n\t\t year: number \n\t\t january?: number | null \n\t\t february?: number | null \n\t\t march?: number | null \n\t\t april?: number | null \n\t\t may?: number | null \n\t\t june?: number | null \n\t\t july?: number | null \n\t\t august?: number | null \n\t\t september?: number | null \n\t\t october?: number | null \n\t\t november?: number | null \n\t\t december?: number | null \n\t }[], \n\t cycles: {\n\t\t station: string \n\t\t month: string \n\t\t mean: number \n\t\t standard_deviation: number \n\t\t percentiles: {\n\t\t\t 2.5: number \n\t\t\t 17: number \n\t\t\t 50: number \n\t\t\t 83: number \n\t\t\t 97.5: number \n\t\t}\n\t }[], \n\t stations: {\n\t\t station: string \n\t\t name: string | null \n\t\t region: string | null \n\t\t country: string \n\t\t latitude: number \n\t\t longitude: number \n\t\t elevation: number | null \n\t }[],\n}",
  "download-ex": "{\n\t prcp: [\n\t\t{\n\t\t\t station: \"71706\" \n\t\t\t year: 1943 \n\t\t\t january: null \n\t\t\t february: null \n\t\t\t march: null \n\t\t},\n\t\t{\n\t\t\t station: \"71706\" \n\t\t\t year: 1944 \n\t\t\t january: 33.0 \n\t\t\t february: 130.3 \n\t\t\t march: 85.3 \n\t\t},\n\t\t{\n\t\t\t station: \"71706.2\" \n\t\t\t year: 1874 \n\t\t\t january: null \n\t\t\t february: 51.3 \n\t\t\t march: 71.4 \n\t\t}\n\t ],\n\t anom: [\n\t\t{\n\t\t\t station: \"71706\" \n\t\t\t year: 1943 \n\t\t\t january: null \n\t\t\t february: null \n\t\t\t march: null \n\t\t},\n\t\t{\n\t\t\t station: \"71706\" \n\t\t\t year: 1944 \n\t\t\t january: -75.502 \n\t\t\t february: 40.275 \n\t\t\t march: -3.089 \n\t\t},\n\t\t{\n\t\t\t station: \"71706.2\" \n\t\t\t year: 1874 \n\t\t\t january: null \n\t\t\t february: -18.508 \n\t\t\t march: -12.186 \n\t\t}\n\t ],\n\t anom_pcnt: [\n\t\t{\n\t\t\t station: \"71706\" \n\t\t\t year: 1943 \n\t\t\t january: null \n\t\t\t february: null \n\t\t\t march: null \n\t\t},\n\t\t{\n\t\t\t station: \"71706\" \n\t\t\t year: 1944 \n\t\t\t january: -69.586 \n\t\t\t february: 44.738 \n\t\t\t march: -3.495 \n\t\t},\n\t\t{\n\t\t\t station: \"71706.2\" \n\t\t\t year: 1874 \n\t\t\t january: null \n\t\t\t february: -26.512 \n\t\t\t march: -14.579 \n\t\t}\n\t ], \n\t cycles: [\n\t\t{\n\t\t\t station: \"71706\" \n\t\t\t month: \"January\" \n\t\t\t mean: 108.502 \n\t\t\t standard_deviation: 43.044 \n\t\t\t percentiles: {\n\t\t\t\t 2.5: 36 \n\t\t\t\t 17: 71.732 \n\t\t\t\t 50: 104.1 \n\t\t\t\t 83: 139.736 \n\t\t\t\t 97.5: 218.32 \n\t\t\t}\n\t\t},\n\t\t{\n\t\t\t station: \"71706\" \n\t\t\t month: \"February\" \n\t\t\t mean: 90.025 \n\t\t\t standard_deviation: 32.927 \n\t\t\t percentiles: {\n\t\t\t\t 2.5: 38.78 \n\t\t\t\t 17: 60.98 \n\t\t\t\t 50: 86.1 \n\t\t\t\t 83: 122.4 \n\t\t\t\t 97.5: 122.4 \n\t\t\t}\n\t\t},\n\t\t{\n\t\t\t station: \"71706\" \n\t\t\t month: \"March\" \n\t\t\t mean: 88.389 \n\t\t\t standard_deviation: 33.111 \n\t\t\t percentiles: {\n\t\t\t\t 2.5: 34.44 \n\t\t\t\t 17: 59.992 \n\t\t\t\t 50: 85.3 \n\t\t\t\t 83: 110.936 \n\t\t\t\t 97.5: 160.24 \n\t\t\t}\n\t\t},\n\t\t{\n\t\t\t station: \"71706.2\" \n\t\t\t month: \"January\" \n\t\t\t mean: 103.438 \n\t\t\t standard_deviation: 47.680 \n\t\t\t percentiles: {\n\t\t\t\t 2.5: 37.15 \n\t\t\t\t 17: 65.084 \n\t\t\t\t 50: 96.5 \n\t\t\t\t 83: 147.44 \n\t\t\t\t 97.5: 198.63 \n\t\t\t}\n\t\t},\n\t\t{\n\t\t\t station: \"71706.2\" \n\t\t\t month: \"February\" \n\t\t\t mean: 69.808 \n\t\t\t standard_deviation: 29.751 \n\t\t\t percentiles: {\n\t\t\t\t 2.5: 31.86 \n\t\t\t\t 17: 43.504 \n\t\t\t\t 50: 61 \n\t\t\t\t 83: 90.768 \n\t\t\t\t 97.5: 128.48 \n\t\t\t}\n\t\t},\n\t\t{\n\t\t\t station: \"71706.2\" \n\t\t\t month: \"March\" \n\t\t\t mean: 83.586 \n\t\t\t standard_deviation: 41.408 \n\t\t\t percentiles: {\n\t\t\t\t 2.5: 24.408 \n\t\t\t\t 17: 38.72 \n\t\t\t\t 50: 75.2 \n\t\t\t\t 83: 113.731 \n\t\t\t\t 97.5: 163.547 \n\t\t\t}\n\t\t}\n\t ],\n\t stations: [\n\t\t{\n\t\t\t station: \"71706\" \n\t\t\t name: \"CHARLOTTETOWN A,PE\" \n\t\t\t region: \"PE\" \n\t\t\t country: \"CANADA\" \n\t\t\t latitude: 46.28 \n\t\t\t longitude: -63.13 \n\t\t\t elevation: 48 \n\t\t},\n\t\t{\n\t\t\t station: \"71706.2\" \n\t\t\t name: \"GEORGETOWN,PE\" \n\t\t\t region: \"PE\" \n\t\t\t country: \"CANADA\" \n\t\t\t latitude: 47.18 \n\t\t\t longitude: -62.58 \n\t\t\t elevation: 12 \n\t\t}\n\t ]\n}"
}