[
  {
      "station": "60354.1",
      "month": "January",
      "mean": "95.78064516129032",
      "standard_deviation": "57.92957581773301",
      "percentiles": [
          8,
          39.18000000000001,
          93,
          148.45999999999998,
          224.95000000000007
      ]
  },
  {
      "station": "60354.1",
      "month": "February",
      "mean": "80.76129032258065",
      "standard_deviation": "62.21628081406884",
      "percentiles": [
          2,
          25.720000000000013,
          72,
          116,
          238.95000000000007
      ]
  },
  {
      "station": "60354.1",
      "month": "March",
      "mean": "70.99358974358974",
      "standard_deviation": "42.80149422189093",
      "percentiles": [
          10.875,
          29.35,
          67.5,
          111.30000000000001,
          165.5
      ]
  },
  {
      "station": "60354.1",
      "month": "April",
      "mean": "55.282051282051285",
      "standard_deviation": "40.3911634902974",
      "percentiles": [
          5.75,
          18,
          47,
          86.30000000000001,
          154.625
      ]
  },
  {
      "station": "60354.1",
      "month": "May",
      "mean": "36.70967741935484",
      "standard_deviation": "31.705900080204966",
      "percentiles": [
          1,
          7,
          28,
          65.82,
          111.45000000000002
      ]
  },
  {
      "station": "60354.1",
      "month": "June",
      "mean": "14.23225806451613",
      "standard_deviation": "16.409603543338022",
      "percentiles": [
          0,
          1,
          8,
          24,
          59.900000000000034
      ]
  },
  {
      "station": "60354.1",
      "month": "July",
      "mean": "2.176470588235294",
      "standard_deviation": "4.569174418154121",
      "percentiles": [
          0,
          0,
          0,
          4.159999999999997,
          15.199999999999989
      ]
  },
  {
      "station": "60354.1",
      "month": "August",
      "mean": "3.1156462585034013",
      "standard_deviation": "5.475383385828405",
      "percentiles": [
          0,
          0,
          1,
          6,
          19.349999999999994
      ]
  },
  {
      "station": "60354.1",
      "month": "September",
      "mean": "29.961038961038962",
      "standard_deviation": "30.884342924556446",
      "percentiles": [
          0,
          4,
          22.5,
          50.989999999999995,
          115.1499999999997
      ]
  },
  {
      "station": "60354.1",
      "month": "October",
      "mean": "75.0",
      "standard_deviation": "55.68719873152269",
      "percentiles": [
          2.875,
          22,
          61,
          129.65,
          199.875
      ]
  },
  {
      "station": "60354.1",
      "month": "November",
      "mean": "100.47096774193548",
      "standard_deviation": "66.84129587722956",
      "percentiles": [
          16.25,
          40.18000000000001,
          85,
          166,
          242.05000000000015
      ]
  },
  {
      "station": "60354.1",
      "month": "December",
      "mean": "115.50649350649351",
      "standard_deviation": "72.89115232800553",
      "percentiles": [
          14.65,
          49.010000000000005,
          100.5,
          187.93999999999997,
          283.5749999999998
      ]
  },
  {
      "station": "60355",
      "month": "January",
      "mean": "112.35394736842102",
      "standard_deviation": "71.27814576267853",
      "percentiles": [
          19.2625,
          47.85,
          97.85,
          168.54999999999998,
          277.625
      ]
  },
  {
      "station": "60355",
      "month": "February",
      "mean": "90.65569620253164",
      "standard_deviation": "47.56902179614254",
      "percentiles": [
          19.650000000000002,
          52.112,
          80,
          126.34399999999997,
          191.45
      ]
  },
  {
      "station": "60355",
      "month": "March",
      "mean": "72.29240506329114",
      "standard_deviation": "118.73445403600562",
      "percentiles": [
          16.89,
          38.262,
          81,
          124.35,
          190.52499999999992
      ]
  },
  {
      "station": "60355",
      "month": "April",
      "mean": "54.685135135135134",
      "standard_deviation": "40.85037193397265",
      "percentiles": [
          4.8975,
          18.123,
          40.95,
          90.84099999999997,
          148.19999999999993
      ]
  },
  {
      "station": "60355",
      "month": "May",
      "mean": "37.62567567567568",
      "standard_deviation": "34.73395044812281",
      "percentiles": [
          2,
          9.115,
          28.35,
          61.35699999999999,
          135.84999999999994
      ]
  },
  {
      "station": "60355",
      "month": "June",
      "mean": "1.0027397260273978",
      "standard_deviation": "106.01037423077372",
      "percentiles": [
          0,
          1.048,
          7.6,
          23.976,
          48.94000000000002
      ]
  },
  {
      "station": "60355",
      "month": "July",
      "mean": "2.441333333333333",
      "standard_deviation": "4.708094967417521",
      "percentiles": [
          0,
          0,
          0,
          5.839999999999989,
          13.299999999999983
      ]
  },
  {
      "station": "60355",
      "month": "August",
      "mean": "10.619736842105262",
      "standard_deviation": "14.792138912779262",
      "percentiles": [
          0,
          0,
          4,
          23.049999999999997,
          48.5
      ]
  },
  {
      "station": "60355",
      "month": "September",
      "mean": "38.699999999999996",
      "standard_deviation": "30.38609300136041",
      "percentiles": [
          0,
          14.24,
          33,
          58.33999999999998,
          106.3
      ]
  },
  {
      "station": "60355",
      "month": "October",
      "mean": "80.54166666666669",
      "standard_deviation": "60.34107857744084",
      "percentiles": [
          3.7750000000000004,
          26.028,
          75.5,
          126.76700000000001,
          215.06249999999955
      ]
  },
  {
      "station": "60355",
      "month": "November",
      "mean": "101.99599999999998",
      "standard_deviation": "56.88994859082461",
      "percentiles": [
          7.0200000000000005,
          44.269999999999996,
          91.8,
          158.08599999999998,
          217.51999999999987
      ]
  },
  {
      "station": "60355",
      "month": "December",
      "mean": "132.3383561643836",
      "standard_deviation": "148.79779294848058",
      "percentiles": [
          8.540000000000001,
          50.516,
          147,
          236.51999999999998,
          314.00000000000006
      ]
  }
]